[
  {
    "name": "Prof. Banchong Mahaisavariya, M.D.",
    "position": "President of Mahidol University",
    "email": "president@Mahidol.ac.th, banchong.mah@mahidol.ac.th",
    "education": "",
    "img": "issets/img/group/mugh/อธิการ.jpg",
    "group": "MUGH Working Group Committee"
  },
  {
    "name": "Assoc. Prof. Dr. Chuthamanee Suthisissang, Ph.D",
    "position": "Vice President of Mahidol University",
    "email": "chuthamanee.sut@mahidol.ac.th",
    "education": "",
    "img": "issets/img/group/mugh/Untitled-4.jpg",
    "group": "MUGH Working Group Committee"
  },
  {
    "name": "Assoc. Prof. Dr. Phudit Tejativaddhana. M.D.",
    "position": "Director of ASEAN Institute for Health Development, Mahidol University",
    "email": "phudit.tej@mahidol.ac.th",
    "education": "",
    "img": "issets/img/group/mugh/จารรร.jpg",
    "group": "MUGH Working Group Committee"
  },
  {
    "name": "Adjunct Prof. Dr. Thaworn Sakunphanit M.D.",
    "position": "Advisor to ASEAN Institute for Health Development, Mahidol University",
    "email": "",
    "education": "",
    "img": "issets/img/group/mugh/จาร.jpg",
    "group": "MUGH Working Group Committee"
  },
  {
    "name": "Asst. Prof. Dr. Walasinee Sakcamduang",
    "position": "Dean of Faculty of Veterinary Science",
    "email": "walasinee.sak@mahidol.edu",
    "education": "",
    "img": "issets/img/group/mugh/จารรรรรร.jpg",
    "group": "MUGH Working Group Committee"
  },
  {
    "name": "Assoc. Prof. Sura Pattanakiat",
    "position": "Dean of Faculty of Faculty of Environmental Resource Studies",
    "email": "deanen@mahidol.ac.th",
    "education": "",
    "img": "issets/img/group/mugh/สุระ.jpg",
    "group": "MUGH Working Group Committee"
  },
  {
    "name": "Dr. Patthanasak Mongkolwat",
    "position": "Dean of Information and Communication Technology",
    "email": "deanic@Mahidol.ac.th",
    "education": "",
    "img": "issets/img/group/mugh/พัฒนศักดิ์.jpg",
    "group": "MUGH Working Group Committee"
  },
  {
    "name": "Asst. Prof. Dr. Supaporn Songpracha",
    "position": "Deputy Director of Academic Affairs",
    "email": "supaporn.sog@mahidol.ac.th",
    "education": "",
    "img": "issets/img/group/mugh/จารสุ.jpg",
    "group": "MUGH Working Group Committee"
  },
  {
    "name": "Asst. Prof. Dr. Mayuree Yotawut",
    "position": "Assistant Director of Academic Affairs",
    "email": "mayuree.yot@mahidol.ac.th",
    "education": "",
    "img": "issets/img/group/mugh/อ.jpg",
    "group": "MUGH Working Group Committee"
  },
  {
    "name": "Lect. Dr. Theerapat Ungsuchawal Ph.D.",
    "position": "Lecturer of  the Faculty of Social Sciences and Humanities",
    "email": "theerapat.ung@Mahidol.ac.th",
    "education": "",
    "img": "issets/img/group/mugh/ธีร.jpg",
    "group": "MUGH Working Group Committee"
  },
  {
    "name": "Assoc. Prof. Dr. Cheerawit Rattanapan",
    "position": "Program Director of Doctor of Philosophy Program in Health and Sustainable Development Committee",
    "email": "cheerawit.rat@mahidol.ac.th",
    "education": "",
    "img": "issets/img/group/mugh/ชีระวิทย์.jpg",
    "group": "MUGH Working Group Committee"
  },
  {
    "name": "Assoc. Prof. Dr. Thunwadee Suksaroj",
    "position": "Representative from Academic Staff Committee",
    "email": "thunwadee.suk@mahidol.ac.th",
    "education": "",
    "img": "issets/img/group/mugh/บี้.jpg",
    "group": "MUGH Working Group Committee"
  },
  {
    "name": "Dr. Vo Thi Hue Man",
    "position": "Assistant Director for International Affairs",
    "email": "man.vo@mahidol.ac.th",
    "education": "",
    "img": "issets/img/group/mugh/man.jpg",
    "group": "MUGH Working Group Committee"
  },
  {
    "name": "Assoc. Prof. Sura Pattanakiat",
    "position": "",
    "email": "deanen@mahidol.ac.th",
    "education": "",
    "img": "issets/img/group/mugh/สุระ.jpg",
    "group": "Climate change, Sustainability, and Global Public Health"
  }
]